CHANGELOG.txt
LICENSE.txt
MANIFEST.in
README.txt
ez_setup.py
setup.cfg
setup.py
HTTPKit.egg-info/PKG-INFO
HTTPKit.egg-info/SOURCES.txt
HTTPKit.egg-info/dependency_links.txt
HTTPKit.egg-info/entry_points.txt
HTTPKit.egg-info/not-zip-safe
HTTPKit.egg-info/requires.txt
HTTPKit.egg-info/top_level.txt
doc/Makefile
doc/index.txt
doc/source/api.rst
doc/source/conf.py
doc/source/index.rst
doc/source/manual.rst
example/README.txt
httpkit/__init__.py
httpkit/helper/__init__.py
httpkit/helper/cookie.py
httpkit/helper/response.py
httpkit/service/__init__.py
httpkit/service/input.py
httpkit/service/not_found.py
httpkit/service/query.py
httpkit/service/response.py
test/README.txt
test/doc.py