Metadata-Version: 1.0
Name: HTTPKit
Version: 0.2.0
Summary: HTTP-related tools to for PipeStack
Home-page: http://jimmyg.org/work/code/httpkit/index.html
Author: James Gardner
Author-email: UNKNOWN
License: AGPLv3
Platform: UNKNOWN
Classifier: Development Status :: 3 - Alpha
Classifier: Environment :: Web Environment
Classifier: License :: OSI Approved :: GNU Affero General Public License v3
Classifier: Programming Language :: Python
